zygoat_django/__init__.py
zygoat_django/apps.py
zygoat_django/management/__init__.py
zygoat_django/management/commands/__init__.py
zygoat_django/management/commands/set_staff.py
zygoat_django/management/commands/wait_for_db.py
zygoat_django/middleware/__init__.py
zygoat_django/middleware/reverse_proxy.py
zygoat_django/middleware/security_headers.py
zygoat_django/middleware/session_expiration.py
zygoat_django/models.py
zygoat_django/settings/__init__.py
zygoat_django/settings/cache.py
zygoat_django/settings/environment.py
zygoat_django/settings/rest_framework.py
zygoat_django/uvicorn_worker.py
zygoat_django-1.0.1.dist-info/WHEEL
zygoat_django-1.0.1.dist-info/METADATA
zygoat_django-1.0.1.dist-info/RECORD
